sipkit/__init__.py
sipkit/__version__.py
sipkit/command_line.py
sipkit/effective_index.py
sipkit/group_index.py
sipkit/permittivity.py
sipkit/read_data.py
sipkit/util.py
sipkit/data/Si_Palik_Refractive_Index.pickle
sipkit/data/neff_fitted_Si_fitted_SiO2_width_240_5_700_wav_1200_0p1_1700.csv
sipkit/data/neff_pol.pickle
sipkit/data/neff_te0_fitted_Si_fitted_SiO2_width_240_10_700_wav_1200_10_1700.csv
sipkit/data/neff_te0_fitted_Si_fitted_SiO2_width_240_5_700_wav_1200_0p1_1700.csv
sipkit/data/neff_te1_fitted_Si_fitted_SiO2_width_240_10_700_wav_1200_10_1700.csv
sipkit/data/neff_te1_fitted_Si_fitted_SiO2_width_240_5_700_wav_1200_0p1_1700.csv
sipkit/data/neff_te2_fitted_Si_fitted_SiO2_width_240_10_700_wav_1200_10_1700.csv
sipkit/data/neff_te2_fitted_Si_fitted_SiO2_width_240_5_700_wav_1200_0p1_1700.csv
sipkit/data/neff_tm0_fitted_Si_fitted_SiO2_width_240_10_700_wav_1200_10_1700.csv
sipkit/data/neff_tm0_fitted_Si_fitted_SiO2_width_240_5_700_wav_1200_0p1_1700.csv
sipkit/data/neff_tm1_fitted_Si_fitted_SiO2_width_240_10_700_wav_1200_10_1700.csv
sipkit/data/neff_tm1_fitted_Si_fitted_SiO2_width_240_5_700_wav_1200_0p1_1700.csv
sipkit/data/permittivity.pkl
sipkit-1.6.0.dist-info/LICENSE
sipkit-1.6.0.dist-info/METADATA
sipkit-1.6.0.dist-info/WHEEL
sipkit-1.6.0.dist-info/top_level.txt
sipkit-1.6.0.dist-info/RECORD
