Metadata-Version: 2.1
Name: sipkit
Version: 1.6.0
Summary: A toolkit to rapidly lookup parameters for the design of silicon photonic components with automatic differentiation capability
Author-email: Aycan Deniz Vit <aycandv@gmail.com>
License: MIT License
Project-URL: Homepage, https://github.com/Photonic-Architecture-Laboratories/si-photonics-toolkit
Keywords: photonics,nanophotonics,silicon photonics
Classifier: License :: OSI Approved :: MIT License
Classifier: Programming Language :: Python
Classifier: Programming Language :: Python :: 3
Classifier: Topic :: Scientific/Engineering :: Physics
Requires-Python: >=3.6
License-File: LICENSE
Requires-Dist: jax
Requires-Dist: jaxlib
Requires-Dist: tomli ; python_version < "3.11"
Provides-Extra: dev
Requires-Dist: pylint ; extra == 'dev'
Requires-Dist: sed ; extra == 'dev'
Requires-Dist: tee ; extra == 'dev'
Requires-Dist: anybadge ; extra == 'dev'
Requires-Dist: isort ; extra == 'dev'
Requires-Dist: pytest ; extra == 'dev'
Requires-Dist: click ; extra == 'dev'
Requires-Dist: black ; extra == 'dev'
Requires-Dist: autoflake ; extra == 'dev'
Requires-Dist: pre-commit ; extra == 'dev'
Requires-Dist: commitizen ; extra == 'dev'
Requires-Dist: pytest-cov ; extra == 'dev'
Requires-Dist: bumpver ; extra == 'dev'
Requires-Dist: pip-tools ; extra == 'dev'
